{
 	"Global Stats":
 	 [ 
		0.0,	3.5,	4.9,	10.7,	80.9
		],
	 "Time History":
	 [
		{"Ts": 0.00, "Te": 0.25, "rms": 0.65, "QDeg": 0.00},
		{"Ts": 0.25, "Te": 0.50, "rms": 0.64, "QDeg": 0.00},
		{"Ts": 0.50, "Te": 0.75, "rms": 0.58, "QDeg": 0.00},
		{"Ts": 0.75, "Te": 1.00, "rms": 0.59, "QDeg": 0.00},
		{"Ts": 1.00, "Te": 1.25, "rms": 0.57, "QDeg": 0.00},
		{"Ts": 1.25, "Te": 1.50, "rms": 0.60, "QDeg": 0.00},
		{"Ts": 1.50, "Te": 1.75, "rms": 0.64, "QDeg": 0.00},
		{"Ts": 1.75, "Te": 2.00, "rms": 0.70, "QDeg": 0.00},
		{"Ts": 2.00, "Te": 2.25, "rms": 0.79, "QDeg": 0.00},
		{"Ts": 2.25, "Te": 2.50, "rms": 0.82, "QDeg": 0.00},
		{"Ts": 2.50, "Te": 2.75, "rms": 0.78, "QDeg": 0.00},
		{"Ts": 2.75, "Te": 3.00, "rms": 0.71, "QDeg": 0.00},
		{"Ts": 3.00, "Te": 3.24, "rms": 0.62, "QDeg": 0.00},
		{"Ts": 3.24, "Te": 3.49, "rms": 0.55, "QDeg": 0.00},
		{"Ts": 3.49, "Te": 3.74, "rms": 0.54, "QDeg": 0.00},
		{"Ts": 3.74, "Te": 3.99, "rms": 0.54, "QDeg": 0.00},
		{"Ts": 3.99, "Te": 4.24, "rms": 0.55, "QDeg": 0.00},
		{"Ts": 4.24, "Te": 4.49, "rms": 0.54, "QDeg": 0.00},
		{"Ts": 4.49, "Te": 4.74, "rms": 0.53, "QDeg": 0.00},
		{"Ts": 4.74, "Te": 4.99, "rms": 0.58, "QDeg": 0.00},
		{"Ts": 4.99, "Te": 5.24, "rms": 0.62, "QDeg": 0.00},
		{"Ts": 5.24, "Te": 5.49, "rms": 0.62, "QDeg": 0.00},
		{"Ts": 5.49, "Te": 5.74, "rms": 0.64, "QDeg": 0.00},
		{"Ts": 5.74, "Te": 5.99, "rms": 0.68, "QDeg": 0.00},
		{"Ts": 5.99, "Te": 6.24, "rms": 0.72, "QDeg": 0.00},
		{"Ts": 6.24, "Te": 6.49, "rms": 0.80, "QDeg": 0.00},
		{"Ts": 6.49, "Te": 6.74, "rms": 0.81, "QDeg": 0.00},
		{"Ts": 6.74, "Te": 6.99, "rms": 0.80, "QDeg": 0.00},
		{"Ts": 6.99, "Te": 7.24, "rms": 0.81, "QDeg": 0.00},
		{"Ts": 7.24, "Te": 7.49, "rms": 0.75, "QDeg": 0.00},
		{"Ts": 7.49, "Te": 7.74, "rms": 0.83, "QDeg": 0.00},
		{"Ts": 7.74, "Te": 7.99, "rms": 0.82, "QDeg": 0.00},
		{"Ts": 7.99, "Te": 8.24, "rms": 0.85, "QDeg": 0.00},
		{"Ts": 8.24, "Te": 8.49, "rms": 0.84, "QDeg": 0.00},
		{"Ts": 8.49, "Te": 8.74, "rms": 0.82, "QDeg": 0.00},
		{"Ts": 8.74, "Te": 8.99, "rms": 0.90, "QDeg": 0.00},
		{"Ts": 8.99, "Te": 9.24, "rms": 0.92, "QDeg": 0.00},
		{"Ts": 9.24, "Te": 9.49, "rms": 0.97, "QDeg": 0.00},
		{"Ts": 9.49, "Te": 9.73, "rms": 0.97, "QDeg": 0.00},
		{"Ts": 9.73, "Te": 9.98, "rms": 0.95, "QDeg": 0.00},
		{"Ts": 9.98, "Te": 10.23, "rms": 0.95, "QDeg": 0.00},
		{"Ts": 10.23, "Te": 10.48, "rms": 1.07, "QDeg": 0.00},
		{"Ts": 10.48, "Te": 10.73, "rms": 1.12, "QDeg": 0.00},
		{"Ts": 10.73, "Te": 10.98, "rms": 1.10, "QDeg": 0.00},
		{"Ts": 10.98, "Te": 11.23, "rms": 1.06, "QDeg": 0.00},
		{"Ts": 11.23, "Te": 11.48, "rms": 0.97, "QDeg": 0.00},
		{"Ts": 11.48, "Te": 11.73, "rms": 0.93, "QDeg": 0.00},
		{"Ts": 11.73, "Te": 11.98, "rms": 1.04, "QDeg": 0.00},
		{"Ts": 11.98, "Te": 12.23, "rms": 1.13, "QDeg": 0.00},
		{"Ts": 12.23, "Te": 12.48, "rms": 1.18, "QDeg": 0.00},
		{"Ts": 12.48, "Te": 12.73, "rms": 1.23, "QDeg": 0.00},
		{"Ts": 12.73, "Te": 12.98, "rms": 1.15, "QDeg": 0.00},
		{"Ts": 12.98, "Te": 13.23, "rms": 1.18, "QDeg": 0.00},
		{"Ts": 13.23, "Te": 13.48, "rms": 1.24, "QDeg": 0.00},
		{"Ts": 13.48, "Te": 13.73, "rms": 1.27, "QDeg": 0.00},
		{"Ts": 13.73, "Te": 13.98, "rms": 1.35, "QDeg": 0.00},
		{"Ts": 13.98, "Te": 14.23, "rms": 1.31, "QDeg": 0.00},
		{"Ts": 14.23, "Te": 14.48, "rms": 1.22, "QDeg": 0.00},
		{"Ts": 14.48, "Te": 14.73, "rms": 1.23, "QDeg": 0.00},
		{"Ts": 14.73, "Te": 14.98, "rms": 1.19, "QDeg": 0.00},
		{"Ts": 14.98, "Te": 15.23, "rms": 1.17, "QDeg": 0.00},
		{"Ts": 15.23, "Te": 15.48, "rms": 1.20, "QDeg": 0.00},
		{"Ts": 15.48, "Te": 15.73, "rms": 1.13, "QDeg": 0.00},
		{"Ts": 15.73, "Te": 15.98, "rms": 1.08, "QDeg": 0.00},
		{"Ts": 15.98, "Te": 16.22, "rms": 1.09, "QDeg": 0.00},
		{"Ts": 16.22, "Te": 16.47, "rms": 1.25, "QDeg": 0.00},
		{"Ts": 16.47, "Te": 16.72, "rms": 1.39, "QDeg": 0.00},
		{"Ts": 16.72, "Te": 16.97, "rms": 1.39, "QDeg": 0.00},
		{"Ts": 16.97, "Te": 17.22, "rms": 1.32, "QDeg": 0.00},
		{"Ts": 17.22, "Te": 17.47, "rms": 1.14, "QDeg": 0.00},
		{"Ts": 17.47, "Te": 17.72, "rms": 0.94, "QDeg": 0.00},
		{"Ts": 17.72, "Te": 17.97, "rms": 0.94, "QDeg": 0.00},
		{"Ts": 17.97, "Te": 18.22, "rms": 1.07, "QDeg": 0.00},
		{"Ts": 18.22, "Te": 18.47, "rms": 1.24, "QDeg": 0.00},
		{"Ts": 18.47, "Te": 18.72, "rms": 1.34, "QDeg": 0.00},
		{"Ts": 18.72, "Te": 18.97, "rms": 1.38, "QDeg": 0.00},
		{"Ts": 18.97, "Te": 19.22, "rms": 1.32, "QDeg": 0.00},
		{"Ts": 19.22, "Te": 19.47, "rms": 1.24, "QDeg": 0.00},
		{"Ts": 19.47, "Te": 19.72, "rms": 1.13, "QDeg": 1.56},
		{"Ts": 19.72, "Te": 19.97, "rms": 1.16, "QDeg": 3.12},
		{"Ts": 19.97, "Te": 20.22, "rms": 1.50, "QDeg": 4.69},
		{"Ts": 20.22, "Te": 20.47, "rms": 1.63, "QDeg": 6.25},
		{"Ts": 20.47, "Te": 20.72, "rms": 1.68, "QDeg": 4.69},
		{"Ts": 20.72, "Te": 20.97, "rms": 1.69, "QDeg": 3.12},
		{"Ts": 20.97, "Te": 21.22, "rms": 1.41, "QDeg": 1.56},
		{"Ts": 21.22, "Te": 21.47, "rms": 1.23, "QDeg": 0.00},
		{"Ts": 21.47, "Te": 21.72, "rms": 1.17, "QDeg": 0.00},
		{"Ts": 21.72, "Te": 21.97, "rms": 1.14, "QDeg": 0.00},
		{"Ts": 21.97, "Te": 22.22, "rms": 1.14, "QDeg": 0.00},
		{"Ts": 22.22, "Te": 22.47, "rms": 1.22, "QDeg": 0.00},
		{"Ts": 22.47, "Te": 22.71, "rms": 1.33, "QDeg": 0.00},
		{"Ts": 22.71, "Te": 22.96, "rms": 1.47, "QDeg": 0.00},
		{"Ts": 22.96, "Te": 23.21, "rms": 1.57, "QDeg": 0.00},
		{"Ts": 23.21, "Te": 23.46, "rms": 1.58, "QDeg": 0.00},
		{"Ts": 23.46, "Te": 23.71, "rms": 1.61, "QDeg": 0.00},
		{"Ts": 23.71, "Te": 23.96, "rms": 1.58, "QDeg": 0.00},
		{"Ts": 23.96, "Te": 24.21, "rms": 1.61, "QDeg": 0.00},
		{"Ts": 24.21, "Te": 24.46, "rms": 1.67, "QDeg": 0.00},
		{"Ts": 24.46, "Te": 24.71, "rms": 1.79, "QDeg": 0.00},
		{"Ts": 24.71, "Te": 24.96, "rms": 1.77, "QDeg": 0.00},
		{"Ts": 24.96, "Te": 25.21, "rms": 1.71, "QDeg": 0.00},
		{"Ts": 25.21, "Te": 25.46, "rms": 1.62, "QDeg": 0.00},
		{"Ts": 25.46, "Te": 25.71, "rms": 1.53, "QDeg": 0.00},
		{"Ts": 25.71, "Te": 25.96, "rms": 1.56, "QDeg": 0.00},
		{"Ts": 25.96, "Te": 26.21, "rms": 1.63, "QDeg": 0.00},
		{"Ts": 26.21, "Te": 26.46, "rms": 1.74, "QDeg": 0.00},
		{"Ts": 26.46, "Te": 26.71, "rms": 1.67, "QDeg": 0.00},
		{"Ts": 26.71, "Te": 26.96, "rms": 1.61, "QDeg": 1.56},
		{"Ts": 26.96, "Te": 27.21, "rms": 1.61, "QDeg": 4.69},
		{"Ts": 27.21, "Te": 27.46, "rms": 1.66, "QDeg": 9.38},
		{"Ts": 27.46, "Te": 27.71, "rms": 1.86, "QDeg": 15.62},
		{"Ts": 27.71, "Te": 27.96, "rms": 1.95, "QDeg": 18.75},
		{"Ts": 27.96, "Te": 28.21, "rms": 1.95, "QDeg": 18.75},
		{"Ts": 28.21, "Te": 28.46, "rms": 1.90, "QDeg": 15.62},
		{"Ts": 28.46, "Te": 28.71, "rms": 1.78, "QDeg": 9.38},
		{"Ts": 28.71, "Te": 28.96, "rms": 1.79, "QDeg": 4.69},
		{"Ts": 28.96, "Te": 29.20, "rms": 1.86, "QDeg": 1.56},
		{"Ts": 29.20, "Te": 29.45, "rms": 1.83, "QDeg": 0.00},
		{"Ts": 29.45, "Te": 29.70, "rms": 1.78, "QDeg": 0.00},
		{"Ts": 29.70, "Te": 29.95, "rms": 1.73, "QDeg": 0.00},
		{"Ts": 29.95, "Te": 30.20, "rms": 1.74, "QDeg": 1.56},
		{"Ts": 30.20, "Te": 30.45, "rms": 1.84, "QDeg": 4.69},
		{"Ts": 30.45, "Te": 30.70, "rms": 1.90, "QDeg": 9.38},
		{"Ts": 30.70, "Te": 30.95, "rms": 2.05, "QDeg": 15.62},
		{"Ts": 30.95, "Te": 31.20, "rms": 2.02, "QDeg": 18.75},
		{"Ts": 31.20, "Te": 31.45, "rms": 1.96, "QDeg": 20.31},
		{"Ts": 31.45, "Te": 31.70, "rms": 2.08, "QDeg": 20.31},
		{"Ts": 31.70, "Te": 31.95, "rms": 1.98, "QDeg": 18.75},
		{"Ts": 31.95, "Te": 32.20, "rms": 2.07, "QDeg": 20.31},
		{"Ts": 32.20, "Te": 32.45, "rms": 2.03, "QDeg": 20.31},
		{"Ts": 32.45, "Te": 32.70, "rms": 2.01, "QDeg": 20.31},
		{"Ts": 32.70, "Te": 32.95, "rms": 2.01, "QDeg": 18.75},
		{"Ts": 32.95, "Te": 33.20, "rms": 1.96, "QDeg": 15.62},
		{"Ts": 33.20, "Te": 33.45, "rms": 2.10, "QDeg": 17.19},
		{"Ts": 33.45, "Te": 33.70, "rms": 2.18, "QDeg": 18.75},
		{"Ts": 33.70, "Te": 33.95, "rms": 2.40, "QDeg": 25.00},
		{"Ts": 33.95, "Te": 34.20, "rms": 2.54, "QDeg": 31.25},
		{"Ts": 34.20, "Te": 34.45, "rms": 2.63, "QDeg": 32.81},
		{"Ts": 34.45, "Te": 34.70, "rms": 2.56, "QDeg": 35.94},
		{"Ts": 34.70, "Te": 34.95, "rms": 2.39, "QDeg": 37.50},
		{"Ts": 34.95, "Te": 35.20, "rms": 2.35, "QDeg": 42.19},
		{"Ts": 35.20, "Te": 35.45, "rms": 2.68, "QDeg": 51.56},
		{"Ts": 35.45, "Te": 35.69, "rms": 2.96, "QDeg": 59.38},
		{"Ts": 35.69, "Te": 35.94, "rms": 3.07, "QDeg": 64.06},
		{"Ts": 35.94, "Te": 36.19, "rms": 3.13, "QDeg": 62.50},
		{"Ts": 36.19, "Te": 36.44, "rms": 2.82, "QDeg": 54.69},
		{"Ts": 36.44, "Te": 36.69, "rms": 2.57, "QDeg": 45.31},
		{"Ts": 36.69, "Te": 36.94, "rms": 2.42, "QDeg": 35.94},
		{"Ts": 36.94, "Te": 37.19, "rms": 2.44, "QDeg": 29.69},
		{"Ts": 37.19, "Te": 37.44, "rms": 2.39, "QDeg": 28.12},
		{"Ts": 37.44, "Te": 37.69, "rms": 2.28, "QDeg": 29.69},
		{"Ts": 37.69, "Te": 37.94, "rms": 2.47, "QDeg": 35.94},
		{"Ts": 37.94, "Te": 38.19, "rms": 2.50, "QDeg": 45.31},
		{"Ts": 38.19, "Te": 38.44, "rms": 2.68, "QDeg": 54.69},
		{"Ts": 38.44, "Te": 38.69, "rms": 3.02, "QDeg": 64.06},
		{"Ts": 38.69, "Te": 38.94, "rms": 3.18, "QDeg": 70.31},
		{"Ts": 38.94, "Te": 39.19, "rms": 3.28, "QDeg": 73.44},
		{"Ts": 39.19, "Te": 39.44, "rms": 3.34, "QDeg": 73.44},
		{"Ts": 39.44, "Te": 39.69, "rms": 3.32, "QDeg": 71.88},
		{"Ts": 39.69, "Te": 39.94, "rms": 3.25, "QDeg": 70.31},
		{"Ts": 39.94, "Te": 40.19, "rms": 3.26, "QDeg": 67.19},
		{"Ts": 40.19, "Te": 40.44, "rms": 3.21, "QDeg": 67.19},
		{"Ts": 40.44, "Te": 40.69, "rms": 3.23, "QDeg": 67.19},
		{"Ts": 40.69, "Te": 40.94, "rms": 3.28, "QDeg": 67.19},
		{"Ts": 40.94, "Te": 41.19, "rms": 3.35, "QDeg": 70.31},
		{"Ts": 41.19, "Te": 41.44, "rms": 3.45, "QDeg": 71.88},
		{"Ts": 41.44, "Te": 41.69, "rms": 3.48, "QDeg": 73.44},
		{"Ts": 41.69, "Te": 41.94, "rms": 3.49, "QDeg": 75.00},
		{"Ts": 41.94, "Te": 42.18, "rms": 3.41, "QDeg": 75.00},
		{"Ts": 42.18, "Te": 42.43, "rms": 3.31, "QDeg": 75.00},
		{"Ts": 42.43, "Te": 42.68, "rms": 3.13, "QDeg": 75.00},
		{"Ts": 42.68, "Te": 42.93, "rms": 3.02, "QDeg": 73.44},
		{"Ts": 42.93, "Te": 43.18, "rms": 2.91, "QDeg": 70.31},
		{"Ts": 43.18, "Te": 43.43, "rms": 2.98, "QDeg": 65.62},
		{"Ts": 43.43, "Te": 43.68, "rms": 2.95, "QDeg": 59.38},
		{"Ts": 43.68, "Te": 43.93, "rms": 2.91, "QDeg": 56.25},
		{"Ts": 43.93, "Te": 44.18, "rms": 2.93, "QDeg": 56.25},
		{"Ts": 44.18, "Te": 44.43, "rms": 2.92, "QDeg": 59.38},
		{"Ts": 44.43, "Te": 44.68, "rms": 3.07, "QDeg": 65.62},
		{"Ts": 44.68, "Te": 44.93, "rms": 3.20, "QDeg": 68.75},
		{"Ts": 44.93, "Te": 45.18, "rms": 3.19, "QDeg": 68.75},
		{"Ts": 45.18, "Te": 45.43, "rms": 3.05, "QDeg": 64.06},
		{"Ts": 45.43, "Te": 45.68, "rms": 2.82, "QDeg": 54.69},
		{"Ts": 45.68, "Te": 45.93, "rms": 2.70, "QDeg": 45.31},
		{"Ts": 45.93, "Te": 46.18, "rms": 2.51, "QDeg": 35.94},
		{"Ts": 46.18, "Te": 46.43, "rms": 2.38, "QDeg": 29.69},
		{"Ts": 46.43, "Te": 46.68, "rms": 2.44, "QDeg": 26.56},
		{"Ts": 46.68, "Te": 46.93, "rms": 2.35, "QDeg": 25.00},
		{"Ts": 46.93, "Te": 47.18, "rms": 2.40, "QDeg": 26.56},
		{"Ts": 47.18, "Te": 47.43, "rms": 2.52, "QDeg": 29.69},
		{"Ts": 47.43, "Te": 47.68, "rms": 2.67, "QDeg": 34.38},
		{"Ts": 47.68, "Te": 47.93, "rms": 2.76, "QDeg": 40.62},
		{"Ts": 47.93, "Te": 48.18, "rms": 2.80, "QDeg": 45.31},
		{"Ts": 48.18, "Te": 48.43, "rms": 2.65, "QDeg": 46.88},
		{"Ts": 48.43, "Te": 48.67, "rms": 2.52, "QDeg": 45.31},
		{"Ts": 48.67, "Te": 48.92, "rms": 2.53, "QDeg": 42.19},
		{"Ts": 48.92, "Te": 49.17, "rms": 2.53, "QDeg": 37.50},
		{"Ts": 49.17, "Te": 49.42, "rms": 2.56, "QDeg": 35.94},
		{"Ts": 49.42, "Te": 49.67, "rms": 2.53, "QDeg": 37.50},
		{"Ts": 49.67, "Te": 49.92, "rms": 2.61, "QDeg": 39.06},
		{"Ts": 49.92, "Te": 50.17, "rms": 2.70, "QDeg": 43.75},
		{"Ts": 50.17, "Te": 50.42, "rms": 2.85, "QDeg": 45.31},
		{"Ts": 50.42, "Te": 50.67, "rms": 2.87, "QDeg": 43.75},
		{"Ts": 50.67, "Te": 50.92, "rms": 2.55, "QDeg": 40.62},
		{"Ts": 50.92, "Te": 51.17, "rms": 2.31, "QDeg": 35.94},
		{"Ts": 51.17, "Te": 51.42, "rms": 2.23, "QDeg": 34.38},
		{"Ts": 51.42, "Te": 51.67, "rms": 2.33, "QDeg": 35.94},
		{"Ts": 51.67, "Te": 51.92, "rms": 2.51, "QDeg": 39.06},
		{"Ts": 51.92, "Te": 52.17, "rms": 2.60, "QDeg": 40.62},
		{"Ts": 52.17, "Te": 52.42, "rms": 2.63, "QDeg": 39.06},
		{"Ts": 52.42, "Te": 52.67, "rms": 2.55, "QDeg": 35.94},
		{"Ts": 52.67, "Te": 52.92, "rms": 2.47, "QDeg": 32.81},
		{"Ts": 52.92, "Te": 53.17, "rms": 2.55, "QDeg": 31.25},
		{"Ts": 53.17, "Te": 53.42, "rms": 2.47, "QDeg": 31.25},
		{"Ts": 53.42, "Te": 53.67, "rms": 2.38, "QDeg": 29.69},
		{"Ts": 53.67, "Te": 53.92, "rms": 2.33, "QDeg": 29.69},
		{"Ts": 53.92, "Te": 54.17, "rms": 2.18, "QDeg": 29.69},
		{"Ts": 54.17, "Te": 54.42, "rms": 2.22, "QDeg": 29.69},
		{"Ts": 54.42, "Te": 54.67, "rms": 2.19, "QDeg": 29.69},
		{"Ts": 54.67, "Te": 54.92, "rms": 2.07, "QDeg": 28.12},
		{"Ts": 54.92, "Te": 55.16, "rms": 1.96, "QDeg": 28.12},
		{"Ts": 55.16, "Te": 55.41, "rms": 1.84, "QDeg": 28.12},
		{"Ts": 55.41, "Te": 55.66, "rms": 2.00, "QDeg": 32.81},
		{"Ts": 55.66, "Te": 55.91, "rms": 2.20, "QDeg": 37.50},
		{"Ts": 55.91, "Te": 56.16, "rms": 2.38, "QDeg": 40.62},
		{"Ts": 56.16, "Te": 56.41, "rms": 2.48, "QDeg": 45.31},
		{"Ts": 56.41, "Te": 56.66, "rms": 2.54, "QDeg": 46.88},
		{"Ts": 56.66, "Te": 56.91, "rms": 2.64, "QDeg": 46.88},
		{"Ts": 56.91, "Te": 57.16, "rms": 2.55, "QDeg": 45.31},
		{"Ts": 57.16, "Te": 57.41, "rms": 2.46, "QDeg": 39.06},
		{"Ts": 57.41, "Te": 57.66, "rms": 2.24, "QDeg": 29.69},
		{"Ts": 57.66, "Te": 57.91, "rms": 1.98, "QDeg": 20.31},
		{"Ts": 57.91, "Te": 58.16, "rms": 1.83, "QDeg": 12.50},
		{"Ts": 58.16, "Te": 58.41, "rms": 1.80, "QDeg": 9.38},
		{"Ts": 58.41, "Te": 58.66, "rms": 1.87, "QDeg": 10.94},
		{"Ts": 58.66, "Te": 58.91, "rms": 1.89, "QDeg": 14.06},
		{"Ts": 58.91, "Te": 59.16, "rms": 1.99, "QDeg": 15.62},
		{"Ts": 59.16, "Te": 59.41, "rms": 1.94, "QDeg": 14.06},
		{"Ts": 59.41, "Te": 59.66, "rms": 1.91, "QDeg": 9.38},
		{"Ts": 59.66, "Te": 59.91, "rms": 1.90, "QDeg": 4.69},
		{"Ts": 59.91, "Te": 60.16, "rms": 1.87, "QDeg": 1.56},
		{"Ts": 60.16, "Te": 60.41, "rms": 1.82, "QDeg": 0.00},
		{"Ts": 60.41, "Te": 60.66, "rms": 1.62, "QDeg": 0.00},
		{"Ts": 60.66, "Te": 60.91, "rms": 1.46, "QDeg": 0.00},
		{"Ts": 60.91, "Te": 61.16, "rms": 1.41, "QDeg": 0.00},
		{"Ts": 61.16, "Te": 61.41, "rms": 1.30, "QDeg": 0.00},
		{"Ts": 61.41, "Te": 61.65, "rms": 1.33, "QDeg": 0.00},
		{"Ts": 61.65, "Te": 61.90, "rms": 1.36, "QDeg": 0.00},
		{"Ts": 61.90, "Te": 62.15, "rms": 1.47, "QDeg": 0.00},
		{"Ts": 62.15, "Te": 62.40, "rms": 1.53, "QDeg": 0.00},
		{"Ts": 62.40, "Te": 62.65, "rms": 1.57, "QDeg": 0.00},
		{"Ts": 62.65, "Te": 62.90, "rms": 1.66, "QDeg": 0.00},
		{"Ts": 62.90, "Te": 63.15, "rms": 1.60, "QDeg": 0.00},
		{"Ts": 63.15, "Te": 63.40, "rms": 1.58, "QDeg": 0.00},
		{"Ts": 63.40, "Te": 63.65, "rms": 1.52, "QDeg": 0.00},
		{"Ts": 63.65, "Te": 63.90, "rms": 1.46, "QDeg": 0.00},
		{"Ts": 63.90, "Te": 64.15, "rms": 1.46, "QDeg": 0.00},
		{"Ts": 64.15, "Te": 64.40, "rms": 1.66, "QDeg": 0.00},
		{"Ts": 64.40, "Te": 64.65, "rms": 1.72, "QDeg": 0.00},
		{"Ts": 64.65, "Te": 64.90, "rms": 1.74, "QDeg": 0.00},
		{"Ts": 64.90, "Te": 65.15, "rms": 1.70, "QDeg": 0.00},
		{"Ts": 65.15, "Te": 65.40, "rms": 1.57, "QDeg": 0.00},
		{"Ts": 65.40, "Te": 65.65, "rms": 1.65, "QDeg": 1.56},
		{"Ts": 65.65, "Te": 65.90, "rms": 1.65, "QDeg": 3.12},
		{"Ts": 65.90, "Te": 66.15, "rms": 1.70, "QDeg": 4.69},
		{"Ts": 66.15, "Te": 66.40, "rms": 1.76, "QDeg": 6.25},
		{"Ts": 66.40, "Te": 66.65, "rms": 1.77, "QDeg": 4.69},
		{"Ts": 66.65, "Te": 66.90, "rms": 1.79, "QDeg": 3.12},
		{"Ts": 66.90, "Te": 67.15, "rms": 1.80, "QDeg": 1.56},
		{"Ts": 67.15, "Te": 67.40, "rms": 1.86, "QDeg": 0.00},
		{"Ts": 67.40, "Te": 67.65, "rms": 1.86, "QDeg": 0.00},
		{"Ts": 67.65, "Te": 67.90, "rms": 1.88, "QDeg": 1.56},
		{"Ts": 67.90, "Te": 68.14, "rms": 1.92, "QDeg": 3.12},
		{"Ts": 68.14, "Te": 68.39, "rms": 1.95, "QDeg": 4.69},
		{"Ts": 68.39, "Te": 68.64, "rms": 1.90, "QDeg": 6.25},
		{"Ts": 68.64, "Te": 68.89, "rms": 1.80, "QDeg": 6.25},
		{"Ts": 68.89, "Te": 69.14, "rms": 1.69, "QDeg": 7.81},
		{"Ts": 69.14, "Te": 69.39, "rms": 1.70, "QDeg": 10.94},
		{"Ts": 69.39, "Te": 69.64, "rms": 1.95, "QDeg": 15.62},
		{"Ts": 69.64, "Te": 69.89, "rms": 2.04, "QDeg": 18.75},
		{"Ts": 69.89, "Te": 70.14, "rms": 1.99, "QDeg": 18.75},
		{"Ts": 70.14, "Te": 70.39, "rms": 1.80, "QDeg": 15.62},
		{"Ts": 70.39, "Te": 70.64, "rms": 1.43, "QDeg": 9.38},
		{"Ts": 70.64, "Te": 70.89, "rms": 1.40, "QDeg": 4.69},
		{"Ts": 70.89, "Te": 71.14, "rms": 1.46, "QDeg": 1.56},
		{"Ts": 71.14, "Te": 71.39, "rms": 1.39, "QDeg": 0.00},
		{"Ts": 71.39, "Te": 71.64, "rms": 1.40, "QDeg": 0.00},
		{"Ts": 71.64, "Te": 71.89, "rms": 1.33, "QDeg": 0.00},
		{"Ts": 71.89, "Te": 72.14, "rms": 1.37, "QDeg": 0.00},
		{"Ts": 72.14, "Te": 72.39, "rms": 1.49, "QDeg": 0.00},
		{"Ts": 72.39, "Te": 72.64, "rms": 1.45, "QDeg": 0.00},
		{"Ts": 72.64, "Te": 72.89, "rms": 1.41, "QDeg": 0.00},
		{"Ts": 72.89, "Te": 73.14, "rms": 1.27, "QDeg": 0.00},
		{"Ts": 73.14, "Te": 73.39, "rms": 1.16, "QDeg": 0.00},
		{"Ts": 73.39, "Te": 73.64, "rms": 1.21, "QDeg": 0.00},
		{"Ts": 73.64, "Te": 73.89, "rms": 1.23, "QDeg": 0.00},
		{"Ts": 73.89, "Te": 74.14, "rms": 1.38, "QDeg": 0.00},
		{"Ts": 74.14, "Te": 74.39, "rms": 1.48, "QDeg": 0.00},
		{"Ts": 74.39, "Te": 74.63, "rms": 1.46, "QDeg": 0.00},
		{"Ts": 74.63, "Te": 74.88, "rms": 1.39, "QDeg": 0.00},
		{"Ts": 74.88, "Te": 75.13, "rms": 1.21, "QDeg": 0.00},
		{"Ts": 75.13, "Te": 75.38, "rms": 1.02, "QDeg": 0.00},
		{"Ts": 75.38, "Te": 75.63, "rms": 1.01, "QDeg": 0.00},
		{"Ts": 75.63, "Te": 75.88, "rms": 1.02, "QDeg": 0.00},
		{"Ts": 75.88, "Te": 76.13, "rms": 1.01, "QDeg": 0.00},
		{"Ts": 76.13, "Te": 76.38, "rms": 1.01, "QDeg": 0.00},
		{"Ts": 76.38, "Te": 76.63, "rms": 1.05, "QDeg": 0.00},
		{"Ts": 76.63, "Te": 76.88, "rms": 1.16, "QDeg": 0.00},
		{"Ts": 76.88, "Te": 77.13, "rms": 1.17, "QDeg": 0.00},
		{"Ts": 77.13, "Te": 77.38, "rms": 1.23, "QDeg": 0.00},
		{"Ts": 77.38, "Te": 77.63, "rms": 1.19, "QDeg": 0.00},
		{"Ts": 77.63, "Te": 77.88, "rms": 1.03, "QDeg": 0.00},
		{"Ts": 77.88, "Te": 78.13, "rms": 0.95, "QDeg": 0.00},
		{"Ts": 78.13, "Te": 78.38, "rms": 0.93, "QDeg": 0.00},
		{"Ts": 78.38, "Te": 78.63, "rms": 0.84, "QDeg": 0.00},
		{"Ts": 78.63, "Te": 78.88, "rms": 0.90, "QDeg": 0.00},
		{"Ts": 78.88, "Te": 79.13, "rms": 0.97, "QDeg": 0.00},
		{"Ts": 79.13, "Te": 79.38, "rms": 0.93, "QDeg": 0.00},
		{"Ts": 79.38, "Te": 79.63, "rms": 0.99, "QDeg": 0.00},
		{"Ts": 79.63, "Te": 79.88, "rms": 1.00, "QDeg": 0.00},
		{"Ts": 79.88, "Te": 80.13, "rms": 1.06, "QDeg": 0.00},
		{"Ts": 80.13, "Te": 80.38, "rms": 1.14, "QDeg": 0.00},
		{"Ts": 80.38, "Te": 80.63, "rms": 1.17, "QDeg": 0.00},
		{"Ts": 80.63, "Te": 80.88, "rms": 1.22, "QDeg": 0.00},
		{"Ts": 80.88, "Te": 81.12, "rms": 1.28, "QDeg": 0.00},
		{"Ts": 81.12, "Te": 81.37, "rms": 1.26, "QDeg": 0.00},
		{"Ts": 81.37, "Te": 81.62, "rms": 1.37, "QDeg": 0.00},
		{"Ts": 81.62, "Te": 81.87, "rms": 1.33, "QDeg": 0.00},
		{"Ts": 81.87, "Te": 82.12, "rms": 1.26, "QDeg": 0.00},
		{"Ts": 82.12, "Te": 82.37, "rms": 1.35, "QDeg": 0.00},
		{"Ts": 82.37, "Te": 82.62, "rms": 1.40, "QDeg": 0.00},
		{"Ts": 82.62, "Te": 82.87, "rms": 1.46, "QDeg": 0.00},
		{"Ts": 82.87, "Te": 83.12, "rms": 1.50, "QDeg": 0.00},
		{"Ts": 83.12, "Te": 83.37, "rms": 1.66, "QDeg": 0.00},
		{"Ts": 83.37, "Te": 83.62, "rms": 1.63, "QDeg": 0.00},
		{"Ts": 83.62, "Te": 83.87, "rms": 1.67, "QDeg": 0.00},
		{"Ts": 83.87, "Te": 84.12, "rms": 1.60, "QDeg": 0.00},
		{"Ts": 84.12, "Te": 84.37, "rms": 1.30, "QDeg": 0.00},
		{"Ts": 84.37, "Te": 84.62, "rms": 1.08, "QDeg": 0.00},
		{"Ts": 84.62, "Te": 84.87, "rms": 1.03, "QDeg": 0.00},
		{"Ts": 84.87, "Te": 85.12, "rms": 1.08, "QDeg": 0.00},
		{"Ts": 85.12, "Te": 85.37, "rms": 1.11, "QDeg": 0.00},
		{"Ts": 85.37, "Te": 85.62, "rms": 1.16, "QDeg": 0.00},
		{"Ts": 85.62, "Te": 85.87, "rms": 1.04, "QDeg": 0.00},
		{"Ts": 85.87, "Te": 86.12, "rms": 0.94, "QDeg": 0.00},
		{"Ts": 86.12, "Te": 86.37, "rms": 0.87, "QDeg": 0.00},
		{"Ts": 86.37, "Te": 86.62, "rms": 0.82, "QDeg": 0.00},
		{"Ts": 86.62, "Te": 86.87, "rms": 0.85, "QDeg": 0.00},
		{"Ts": 86.87, "Te": 87.12, "rms": 0.86, "QDeg": 0.00},
		{"Ts": 87.12, "Te": 87.37, "rms": 1.06, "QDeg": 0.00},
		{"Ts": 87.37, "Te": 87.61, "rms": 1.09, "QDeg": 0.00},
		{"Ts": 87.61, "Te": 87.86, "rms": 1.14, "QDeg": 0.00},
		{"Ts": 87.86, "Te": 88.11, "rms": 1.21, "QDeg": 0.00},
		{"Ts": 88.11, "Te": 88.36, "rms": 1.05, "QDeg": 0.00},
		{"Ts": 88.36, "Te": 88.61, "rms": 0.98, "QDeg": 0.00},
		{"Ts": 88.61, "Te": 88.86, "rms": 0.86, "QDeg": 0.00},
		{"Ts": 88.86, "Te": 89.11, "rms": 0.73, "QDeg": 0.00},
		{"Ts": 89.11, "Te": 89.36, "rms": 0.74, "QDeg": 0.00},
		{"Ts": 89.36, "Te": 89.61, "rms": 0.74, "QDeg": 0.00},
		{"Ts": 89.61, "Te": 89.86, "rms": 0.79, "QDeg": 0.00},
		{"Ts": 89.86, "Te": 90.11, "rms": 0.87, "QDeg": 0.00},
		{"Ts": 90.11, "Te": 90.36, "rms": 0.88, "QDeg": 1.56},
		{"Ts": 90.36, "Te": 90.61, "rms": 0.90, "QDeg": 4.69},
		{"Ts": 90.61, "Te": 90.86, "rms": 0.90, "QDeg": 7.81},
		{"Ts": 90.86, "Te": 91.11, "rms": 1.44, "QDeg": 10.94},
		{"Ts": 91.11, "Te": 91.36, "rms": 1.56, "QDeg": 10.94},
		{"Ts": 91.36, "Te": 91.61, "rms": 1.55, "QDeg": 7.81},
		{"Ts": 91.61, "Te": 91.86, "rms": 1.53, "QDeg": 4.69},
		{"Ts": 91.86, "Te": 92.11, "rms": 0.96, "QDeg": 1.56},
		{"Ts": 92.11, "Te": 92.36, "rms": 0.71, "QDeg": 0.00},
		{"Ts": 92.36, "Te": 92.61, "rms": 0.83, "QDeg": 0.00},
		{"Ts": 92.61, "Te": 92.86, "rms": 0.82, "QDeg": 0.00},
		{"Ts": 92.86, "Te": 93.11, "rms": 0.80, "QDeg": 0.00},
		{"Ts": 93.11, "Te": 93.36, "rms": 0.72, "QDeg": 0.00},
		{"Ts": 93.36, "Te": 93.61, "rms": 0.56, "QDeg": 0.00},
		{"Ts": 93.61, "Te": 93.86, "rms": 0.53, "QDeg": 0.00},
		{"Ts": 93.86, "Te": 94.10, "rms": 0.53, "QDeg": 0.00},
		{"Ts": 94.10, "Te": 94.35, "rms": 0.50, "QDeg": 0.00},
		{"Ts": 94.35, "Te": 94.60, "rms": 0.52, "QDeg": 0.00},
		{"Ts": 94.60, "Te": 94.85, "rms": 0.50, "QDeg": 0.00},
		{"Ts": 94.85, "Te": 95.10, "rms": 0.52, "QDeg": 0.00},
		{"Ts": 95.10, "Te": 95.35, "rms": 0.55, "QDeg": 0.00},
		{"Ts": 95.35, "Te": 95.60, "rms": 0.54, "QDeg": 0.00},
		{"Ts": 95.60, "Te": 95.85, "rms": 0.55, "QDeg": 0.00},
		{"Ts": 95.85, "Te": 96.10, "rms": 0.54, "QDeg": 0.00},
		{"Ts": 96.10, "Te": 96.35, "rms": 0.53, "QDeg": 0.00},
		{"Ts": 96.35, "Te": 96.60, "rms": 0.52, "QDeg": 0.00},
		{"Ts": 96.60, "Te": 96.85, "rms": 0.52, "QDeg": 0.00},
		{"Ts": 96.85, "Te": 97.10, "rms": 0.53, "QDeg": 0.00},
		{"Ts": 97.10, "Te": 97.35, "rms": 0.53, "QDeg": 0.00},
		{"Ts": 97.35, "Te": 97.60, "rms": 0.55, "QDeg": 0.00},
		{"Ts": 97.60, "Te": 97.85, "rms": 0.54, "QDeg": 0.00},
		{"Ts": 97.85, "Te": 98.10, "rms": 0.50, "QDeg": 0.00},
		{"Ts": 98.10, "Te": 98.35, "rms": 0.49, "QDeg": 0.00},
		{"Ts": 98.35, "Te": 98.60, "rms": 0.47, "QDeg": 0.00},
		{"Ts": 98.60, "Te": 98.85, "rms": 0.47, "QDeg": 0.00},
		{"Ts": 98.85, "Te": 99.10, "rms": 0.48, "QDeg": 0.00},
		{"Ts": 99.10, "Te": 99.35, "rms": 0.51, "QDeg": 0.00},
		{"Ts": 99.35, "Te": 99.60, "rms": 0.52, "QDeg": 0.00},
		{"Ts": 99.60, "Te": 99.85, "rms": 0.56, "QDeg": 0.00},
		{"Ts": 99.85, "Te": 100.10, "rms": 0.60, "QDeg": 0.00},
		{"Ts": 100.10, "Te": 100.35, "rms": 0.60, "QDeg": 0.00},
		{"Ts": 100.35, "Te": 100.59, "rms": 0.63, "QDeg": 0.00},
		{"Ts": 100.59, "Te": 100.84, "rms": 0.63, "QDeg": 0.00},
		{"Ts": 100.84, "Te": 101.09, "rms": 0.60, "QDeg": 0.00},
		{"Ts": 101.09, "Te": 101.34, "rms": 0.60, "QDeg": 0.00},
		{"Ts": 101.34, "Te": 101.59, "rms": 0.57, "QDeg": 0.00},
		{"Ts": 101.59, "Te": 101.84, "rms": 0.56, "QDeg": 0.00},
		{"Ts": 101.84, "Te": 102.09, "rms": 0.58, "QDeg": 0.00},
		{"Ts": 102.09, "Te": 102.34, "rms": 0.57, "QDeg": 0.00},
		{"Ts": 102.34, "Te": 102.59, "rms": 0.60, "QDeg": 0.00},
		{"Ts": 102.59, "Te": 102.84, "rms": 0.59, "QDeg": 0.00},
		{"Ts": 102.84, "Te": 103.09, "rms": 0.60, "QDeg": 0.00},
		{"Ts": 103.09, "Te": 103.34, "rms": 0.57, "QDeg": 0.00},
		{"Ts": 103.34, "Te": 103.59, "rms": 0.69, "QDeg": 0.00},
		{"Ts": 103.59, "Te": 103.84, "rms": 0.71, "QDeg": 0.00},
		{"Ts": 103.84, "Te": 104.09, "rms": 0.77, "QDeg": 0.00},
		{"Ts": 104.09, "Te": 104.34, "rms": 0.79, "QDeg": 0.00},
		{"Ts": 104.34, "Te": 104.59, "rms": 0.90, "QDeg": 0.00},
		{"Ts": 104.59, "Te": 104.84, "rms": 0.94, "QDeg": 0.00},
		{"Ts": 104.84, "Te": 105.09, "rms": 0.97, "QDeg": 0.00},
		{"Ts": 105.09, "Te": 105.34, "rms": 0.99, "QDeg": 0.00},
		{"Ts": 105.34, "Te": 105.59, "rms": 0.86, "QDeg": 0.00},
		{"Ts": 105.59, "Te": 105.84, "rms": 0.82, "QDeg": 0.00},
		{"Ts": 105.84, "Te": 106.09, "rms": 0.70, "QDeg": 0.00},
		{"Ts": 106.09, "Te": 106.34, "rms": 0.68, "QDeg": 0.00},
		{"Ts": 106.34, "Te": 106.59, "rms": 0.58, "QDeg": 0.00},
		{"Ts": 106.59, "Te": 106.84, "rms": 0.56, "QDeg": 0.00},
		{"Ts": 106.84, "Te": 107.08, "rms": 0.55, "QDeg": 0.00},
		{"Ts": 107.08, "Te": 107.33, "rms": 0.56, "QDeg": 0.00},
		{"Ts": 107.33, "Te": 107.58, "rms": 0.55, "QDeg": 0.00},
		{"Ts": 107.58, "Te": 107.83, "rms": 0.57, "QDeg": 0.00},
		{"Ts": 107.83, "Te": 108.08, "rms": 0.56, "QDeg": 0.00},
		{"Ts": 108.08, "Te": 108.33, "rms": 0.54, "QDeg": 0.00},
		{"Ts": 108.33, "Te": 108.58, "rms": 0.52, "QDeg": 0.00},
		{"Ts": 108.58, "Te": 108.83, "rms": 0.49, "QDeg": 0.00},
		{"Ts": 108.83, "Te": 109.08, "rms": 0.48, "QDeg": 0.00},
		{"Ts": 109.08, "Te": 109.33, "rms": 0.47, "QDeg": 0.00},
		{"Ts": 109.33, "Te": 109.58, "rms": 0.47, "QDeg": 0.00},
		{"Ts": 109.58, "Te": 109.83, "rms": 0.47, "QDeg": 0.00},
		{"Ts": 109.83, "Te": 110.08, "rms": 0.48, "QDeg": 0.00},
		{"Ts": 110.08, "Te": 110.33, "rms": 0.49, "QDeg": 0.00},
		{"Ts": 110.33, "Te": 110.58, "rms": 0.51, "QDeg": 0.00},
		{"Ts": 110.58, "Te": 110.83, "rms": 0.49, "QDeg": 0.00},
		{"Ts": 110.83, "Te": 111.08, "rms": 0.49, "QDeg": 0.00},
		{"Ts": 111.08, "Te": 111.33, "rms": 0.49, "QDeg": 0.00},
		{"Ts": 111.33, "Te": 111.58, "rms": 0.48, "QDeg": 1.56},
		{"Ts": 111.58, "Te": 111.83, "rms": 0.49, "QDeg": 4.69},
		{"Ts": 111.83, "Te": 112.08, "rms": 0.51, "QDeg": 7.81},
		{"Ts": 112.08, "Te": 112.33, "rms": 0.52, "QDeg": 10.94},
		{"Ts": 112.33, "Te": 112.58, "rms": 0.55, "QDeg": 10.94},
		{"Ts": 112.58, "Te": 112.83, "rms": 0.64, "QDeg": 7.81},
		{"Ts": 112.83, "Te": 113.08, "rms": 0.64, "QDeg": 4.69},
		{"Ts": 113.08, "Te": 113.32, "rms": 0.62, "QDeg": 1.56},
		{"Ts": 113.32, "Te": 113.57, "rms": 0.60, "QDeg": 0.00},
		{"Ts": 113.57, "Te": 113.82, "rms": 0.51, "QDeg": 0.00},
		{"Ts": 113.82, "Te": 114.07, "rms": 0.51, "QDeg": 0.00},
		{"Ts": 114.07, "Te": 114.32, "rms": 0.55, "QDeg": 0.00},
		{"Ts": 114.32, "Te": 114.57, "rms": 0.56, "QDeg": 0.00},
		{"Ts": 114.57, "Te": 114.82, "rms": 0.52, "QDeg": 0.00},
		{"Ts": 114.82, "Te": 115.07, "rms": 0.49, "QDeg": 0.00},
		{"Ts": 115.07, "Te": 115.32, "rms": 0.44, "QDeg": 1.56},
		{"Ts": 115.32, "Te": 115.57, "rms": 0.43, "QDeg": 3.12},
		{"Ts": 115.57, "Te": 115.82, "rms": 0.44, "QDeg": 6.25},
		{"Ts": 115.82, "Te": 116.07, "rms": 0.44, "QDeg": 9.38},
		{"Ts": 116.07, "Te": 116.32, "rms": 0.48, "QDeg": 9.38},
		{"Ts": 116.32, "Te": 116.57, "rms": 0.49, "QDeg": 9.38},
		{"Ts": 116.57, "Te": 116.82, "rms": 0.48, "QDeg": 6.25},
		{"Ts": 116.82, "Te": 117.07, "rms": 0.48, "QDeg": 3.12},
		{"Ts": 117.07, "Te": 117.32, "rms": 0.43, "QDeg": 1.56},
		{"Ts": 117.32, "Te": 117.57, "rms": 0.40, "QDeg": 0.00},
		{"Ts": 117.57, "Te": 117.82, "rms": 0.39, "QDeg": 0.00},
		{"Ts": 117.82, "Te": 118.07, "rms": 0.40, "QDeg": 1.56},
		{"Ts": 118.07, "Te": 118.32, "rms": 0.41, "QDeg": 3.12},
		{"Ts": 118.32, "Te": 118.57, "rms": 0.41, "QDeg": 4.69},
		{"Ts": 118.57, "Te": 118.82, "rms": 0.41, "QDeg": 6.25},
		{"Ts": 118.82, "Te": 119.07, "rms": 0.39, "QDeg": 4.69},
		{"Ts": 119.07, "Te": 119.32, "rms": 0.36, "QDeg": 4.69},
		{"Ts": 119.32, "Te": 119.57, "rms": 0.36, "QDeg": 4.69},
		{"Ts": 119.57, "Te": 119.81, "rms": 0.35, "QDeg": 4.69},
		{"Ts": 119.81, "Te": 120.06, "rms": 0.40, "QDeg": 7.81},
		{"Ts": 120.06, "Te": 120.31, "rms": 0.41, "QDeg": 7.81},
		{"Ts": 120.31, "Te": 120.56, "rms": 0.42, "QDeg": 7.81},
		{"Ts": 120.56, "Te": 120.81, "rms": 0.42, "QDeg": 9.38},
		{"Ts": 120.81, "Te": 121.06, "rms": 0.40, "QDeg": 9.38},
		{"Ts": 121.06, "Te": 121.31, "rms": 0.39, "QDeg": 12.50},
		{"Ts": 121.31, "Te": 121.56, "rms": 0.39, "QDeg": 15.62},
		{"Ts": 121.56, "Te": 121.81, "rms": 0.38, "QDeg": 15.62},
		{"Ts": 121.81, "Te": 122.06, "rms": 0.42, "QDeg": 15.62},
		{"Ts": 122.06, "Te": 122.31, "rms": 0.41, "QDeg": 12.50},
		{"Ts": 122.31, "Te": 122.56, "rms": 0.41, "QDeg": 9.38},
		{"Ts": 122.56, "Te": 122.81, "rms": 0.41, "QDeg": 7.81},
		{"Ts": 122.81, "Te": 123.06, "rms": 0.40, "QDeg": 4.69},
		{"Ts": 123.06, "Te": 123.31, "rms": 0.45, "QDeg": 3.12},
		{"Ts": 123.31, "Te": 123.56, "rms": 0.54, "QDeg": 1.56},
		{"Ts": 123.56, "Te": 123.81, "rms": 0.57, "QDeg": 0.00},
		{"Ts": 123.81, "Te": 124.06, "rms": 0.57, "QDeg": 0.00},
		{"Ts": 124.06, "Te": 124.31, "rms": 0.58, "QDeg": 0.00},
		{"Ts": 124.31, "Te": 124.56, "rms": 0.58, "QDeg": 0.00},
		{"Ts": 124.56, "Te": 124.81, "rms": 0.61, "QDeg": 0.00},
		{"Ts": 124.81, "Te": 125.06, "rms": 0.60, "QDeg": 0.00},
		{"Ts": 125.06, "Te": 125.31, "rms": 0.58, "QDeg": 0.00},
		{"Ts": 125.31, "Te": 125.56, "rms": 0.51, "QDeg": 0.00},
		{"Ts": 125.56, "Te": 125.81, "rms": 0.45, "QDeg": 0.00},
		{"Ts": 125.81, "Te": 126.06, "rms": 0.42, "QDeg": 0.00},
		{"Ts": 126.06, "Te": 126.30, "rms": 0.41, "QDeg": 0.00},
		{"Ts": 126.30, "Te": 126.55, "rms": 0.45, "QDeg": 0.00},
		{"Ts": 126.55, "Te": 126.80, "rms": 0.50, "QDeg": 0.00},
		{"Ts": 126.80, "Te": 127.05, "rms": 0.52, "QDeg": 0.00},
		{"Ts": 127.05, "Te": 127.30, "rms": 0.51, "QDeg": 0.00},
		{"Ts": 127.30, "Te": 127.55, "rms": 0.49, "QDeg": 0.00},
		{"Ts": 127.55, "Te": 127.80, "rms": 0.46, "QDeg": 0.00},
		{"Ts": 127.80, "Te": 128.05, "rms": 0.42, "QDeg": 0.00},
		{"Ts": 128.05, "Te": 128.30, "rms": 0.41, "QDeg": 0.00},
		{"Ts": 128.30, "Te": 128.55, "rms": 0.44, "QDeg": 0.00},
		{"Ts": 128.55, "Te": 128.80, "rms": 0.46, "QDeg": 0.00},
		{"Ts": 128.80, "Te": 129.05, "rms": 0.47, "QDeg": 0.00},
		{"Ts": 129.05, "Te": 129.30, "rms": 0.49, "QDeg": 0.00},
		{"Ts": 129.30, "Te": 129.55, "rms": 0.44, "QDeg": 0.00},
		{"Ts": 129.55, "Te": 129.80, "rms": 0.43, "QDeg": 0.00},
		{"Ts": 129.80, "Te": 130.05, "rms": 0.42, "QDeg": 0.00},
		{"Ts": 130.05, "Te": 130.30, "rms": 0.42, "QDeg": 0.00},
		{"Ts": 130.30, "Te": 130.55, "rms": 0.42, "QDeg": 0.00},
		{"Ts": 130.55, "Te": 130.80, "rms": 0.41, "QDeg": 0.00},
		{"Ts": 130.80, "Te": 131.05, "rms": 0.47, "QDeg": 0.00},
		{"Ts": 131.05, "Te": 131.30, "rms": 0.54, "QDeg": 0.00},
		{"Ts": 131.30, "Te": 131.55, "rms": 0.63, "QDeg": 0.00},
		{"Ts": 131.55, "Te": 131.80, "rms": 0.65, "QDeg": 0.00},
		{"Ts": 131.80, "Te": 132.05, "rms": 0.64, "QDeg": 0.00},
		{"Ts": 132.05, "Te": 132.30, "rms": 0.60, "QDeg": 0.00},
		{"Ts": 132.30, "Te": 132.55, "rms": 0.58, "QDeg": 0.00},
		{"Ts": 132.55, "Te": 132.79, "rms": 0.62, "QDeg": 0.00},
		{"Ts": 132.79, "Te": 133.04, "rms": 0.65, "QDeg": 0.00},
		{"Ts": 133.04, "Te": 133.29, "rms": 0.69, "QDeg": 0.00},
		{"Ts": 133.29, "Te": 133.54, "rms": 0.71, "QDeg": 0.00},
		{"Ts": 133.54, "Te": 133.79, "rms": 0.72, "QDeg": 0.00},
		{"Ts": 133.79, "Te": 134.04, "rms": 0.74, "QDeg": 0.00},
		{"Ts": 134.04, "Te": 134.29, "rms": 0.75, "QDeg": 0.00},
		{"Ts": 134.29, "Te": 134.54, "rms": 0.81, "QDeg": 0.00},
		{"Ts": 134.54, "Te": 134.79, "rms": 0.90, "QDeg": 0.00},
		{"Ts": 134.79, "Te": 135.04, "rms": 1.00, "QDeg": 0.00},
		{"Ts": 135.04, "Te": 135.29, "rms": 1.14, "QDeg": 0.00},
		{"Ts": 135.29, "Te": 135.54, "rms": 1.18, "QDeg": 0.00},
		{"Ts": 135.54, "Te": 135.79, "rms": 1.18, "QDeg": 0.00},
		{"Ts": 135.79, "Te": 136.04, "rms": 1.22, "QDeg": 0.00},
		{"Ts": 136.04, "Te": 136.29, "rms": 1.21, "QDeg": 0.00},
		{"Ts": 136.29, "Te": 136.54, "rms": 1.35, "QDeg": 0.00},
		{"Ts": 136.54, "Te": 136.79, "rms": 1.51, "QDeg": 0.00},
		{"Ts": 136.79, "Te": 137.04, "rms": 1.56, "QDeg": 0.00},
		{"Ts": 137.04, "Te": 137.29, "rms": 1.56, "QDeg": 0.00},
		{"Ts": 137.29, "Te": 137.54, "rms": 1.43, "QDeg": 0.00},
		{"Ts": 137.54, "Te": 137.79, "rms": 1.31, "QDeg": 0.00},
		{"Ts": 137.79, "Te": 138.04, "rms": 1.26, "QDeg": 0.00},
		{"Ts": 138.04, "Te": 138.29, "rms": 1.26, "QDeg": 0.00},
		{"Ts": 138.29, "Te": 138.54, "rms": 1.29, "QDeg": 0.00},
		{"Ts": 138.54, "Te": 138.79, "rms": 1.47, "QDeg": 0.00},
		{"Ts": 138.79, "Te": 139.04, "rms": 1.55, "QDeg": 0.00},
		{"Ts": 139.04, "Te": 139.28, "rms": 1.57, "QDeg": 0.00},
		{"Ts": 139.28, "Te": 139.53, "rms": 1.55, "QDeg": 0.00},
		{"Ts": 139.53, "Te": 139.78, "rms": 1.37, "QDeg": 0.00},
		{"Ts": 139.78, "Te": 140.03, "rms": 1.16, "QDeg": 0.00},
		{"Ts": 140.03, "Te": 140.28, "rms": 1.02, "QDeg": 0.00},
		{"Ts": 140.28, "Te": 140.53, "rms": 0.89, "QDeg": 0.00},
		{"Ts": 140.53, "Te": 140.78, "rms": 0.70, "QDeg": 0.00},
		{"Ts": 140.78, "Te": 141.03, "rms": 0.67, "QDeg": 0.00},
		{"Ts": 141.03, "Te": 141.28, "rms": 0.60, "QDeg": 0.00},
		{"Ts": 141.28, "Te": 141.53, "rms": 0.57, "QDeg": 0.00},
		{"Ts": 141.53, "Te": 141.78, "rms": 0.56, "QDeg": 0.00},
		{"Ts": 141.78, "Te": 142.03, "rms": 0.57, "QDeg": 0.00},
		{"Ts": 142.03, "Te": 142.28, "rms": 0.61, "QDeg": 0.00},
		{"Ts": 142.28, "Te": 142.53, "rms": 0.62, "QDeg": 0.00},
		{"Ts": 142.53, "Te": 142.78, "rms": 0.61, "QDeg": 0.00},
		{"Ts": 142.78, "Te": 143.03, "rms": 0.63, "QDeg": 0.00},
		{"Ts": 143.03, "Te": 143.28, "rms": 0.65, "QDeg": 0.00},
		{"Ts": 143.28, "Te": 143.53, "rms": 0.83, "QDeg": 0.00},
		{"Ts": 143.53, "Te": 143.78, "rms": 0.93, "QDeg": 0.00},
		{"Ts": 143.78, "Te": 144.03, "rms": 0.93, "QDeg": 0.00},
		{"Ts": 144.03, "Te": 144.28, "rms": 0.90, "QDeg": 0.00},
		{"Ts": 144.28, "Te": 144.53, "rms": 0.69, "QDeg": 0.00},
		{"Ts": 144.53, "Te": 144.78, "rms": 0.54, "QDeg": 0.00},
		{"Ts": 144.78, "Te": 145.03, "rms": 0.46, "QDeg": 0.00},
		{"Ts": 145.03, "Te": 145.28, "rms": 0.38, "QDeg": 0.00},
		{"Ts": 145.28, "Te": 145.53, "rms": 0.38, "QDeg": 0.00},
		{"Ts": 145.53, "Te": 145.77, "rms": 0.37, "QDeg": 0.00},
		{"Ts": 145.77, "Te": 146.02, "rms": 0.41, "QDeg": 0.00},
		{"Ts": 146.02, "Te": 146.27, "rms": 0.42, "QDeg": 0.00},
		{"Ts": 146.27, "Te": 146.52, "rms": 0.44, "QDeg": 0.00},
		{"Ts": 146.52, "Te": 146.77, "rms": 0.46, "QDeg": 0.00},
		{"Ts": 146.77, "Te": 147.02, "rms": 0.46, "QDeg": 0.00},
		{"Ts": 147.02, "Te": 147.27, "rms": 0.47, "QDeg": 0.00},
		{"Ts": 147.27, "Te": 147.52, "rms": 0.47, "QDeg": 0.00},
		{"Ts": 147.52, "Te": 147.77, "rms": 0.45, "QDeg": 0.00},
		{"Ts": 147.77, "Te": 148.02, "rms": 0.42, "QDeg": 0.00},
		{"Ts": 148.02, "Te": 148.27, "rms": 0.44, "QDeg": 0.00},
		{"Ts": 148.27, "Te": 148.52, "rms": 0.43, "QDeg": 0.00},
		{"Ts": 148.52, "Te": 148.77, "rms": 0.43, "QDeg": 0.00},
		{"Ts": 148.77, "Te": 149.02, "rms": 0.43, "QDeg": 0.00},
		{"Ts": 149.02, "Te": 149.27, "rms": 0.42, "QDeg": 1.56},
		{"Ts": 149.27, "Te": 149.52, "rms": 0.41, "QDeg": 3.12},
		{"Ts": 149.52, "Te": 149.77, "rms": 0.49, "QDeg": 6.25},
		{"Ts": 149.77, "Te": 150.02, "rms": 1.14, "QDeg": 10.94},
		{"Ts": 150.02, "Te": 150.27, "rms": 1.60, "QDeg": 12.50},
		{"Ts": 150.27, "Te": 150.52, "rms": 1.76, "QDeg": 15.62},
		{"Ts": 150.52, "Te": 150.77, "rms": 1.97, "QDeg": 17.19},
		{"Ts": 150.77, "Te": 151.02, "rms": 2.04, "QDeg": 18.75},
		{"Ts": 151.02, "Te": 151.27, "rms": 2.12, "QDeg": 23.44},
		{"Ts": 151.27, "Te": 151.52, "rms": 2.15, "QDeg": 26.56},
		{"Ts": 151.52, "Te": 151.77, "rms": 2.27, "QDeg": 29.69},
		{"Ts": 151.77, "Te": 152.02, "rms": 2.51, "QDeg": 29.69},
		{"Ts": 152.02, "Te": 152.26, "rms": 2.69, "QDeg": 29.69},
		{"Ts": 152.26, "Te": 152.51, "rms": 2.80, "QDeg": 28.12},
		{"Ts": 152.51, "Te": 152.76, "rms": 2.62, "QDeg": 25.00},
		{"Ts": 152.76, "Te": 153.01, "rms": 2.32, "QDeg": 21.88},
		{"Ts": 153.01, "Te": 153.26, "rms": 1.77, "QDeg": 14.06},
		{"Ts": 153.26, "Te": 153.51, "rms": 1.47, "QDeg": 7.81},
		{"Ts": 153.51, "Te": 153.76, "rms": 1.37, "QDeg": 3.12},
		{"Ts": 153.76, "Te": 154.01, "rms": 1.00, "QDeg": 0.00},
		{"Ts": 154.01, "Te": 154.26, "rms": 0.93, "QDeg": 0.00},
		{"Ts": 154.26, "Te": 154.51, "rms": 0.89, "QDeg": 0.00},
		{"Ts": 154.51, "Te": 154.76, "rms": 1.29, "QDeg": 1.56},
		{"Ts": 154.76, "Te": 155.01, "rms": 1.47, "QDeg": 4.69},
		{"Ts": 155.01, "Te": 155.26, "rms": 1.84, "QDeg": 9.38},
		{"Ts": 155.26, "Te": 155.51, "rms": 1.92, "QDeg": 15.62},
		{"Ts": 155.51, "Te": 155.76, "rms": 1.78, "QDeg": 20.31},
		{"Ts": 155.76, "Te": 156.01, "rms": 2.05, "QDeg": 23.44},
		{"Ts": 156.01, "Te": 156.26, "rms": 1.93, "QDeg": 23.44},
		{"Ts": 156.26, "Te": 156.51, "rms": 1.91, "QDeg": 20.31},
		{"Ts": 156.51, "Te": 156.76, "rms": 1.89, "QDeg": 15.62},
		{"Ts": 156.76, "Te": 157.01, "rms": 1.39, "QDeg": 9.38},
		{"Ts": 157.01, "Te": 157.26, "rms": 1.09, "QDeg": 4.69},
		{"Ts": 157.26, "Te": 157.51, "rms": 0.90, "QDeg": 1.56},
		{"Ts": 157.51, "Te": 157.76, "rms": 0.93, "QDeg": 0.00},
		{"Ts": 157.76, "Te": 158.01, "rms": 1.02, "QDeg": 0.00},
		{"Ts": 158.01, "Te": 158.26, "rms": 1.07, "QDeg": 0.00},
		{"Ts": 158.26, "Te": 158.51, "rms": 1.06, "QDeg": 0.00},
		{"Ts": 158.51, "Te": 158.75, "rms": 0.88, "QDeg": 0.00},
		{"Ts": 158.75, "Te": 159.00, "rms": 0.83, "QDeg": 0.00},
		{"Ts": 159.00, "Te": 159.25, "rms": 0.79, "QDeg": 0.00},
		{"Ts": 159.25, "Te": 159.50, "rms": 0.79, "QDeg": 0.00},
		{"Ts": 159.50, "Te": 159.75, "rms": 0.75, "QDeg": 0.00},
		{"Ts": 159.75, "Te": 160.00, "rms": 0.66, "QDeg": 0.00},
		{"Ts": 160.00, "Te": 160.25, "rms": 0.57, "QDeg": 0.00},
		{"Ts": 160.25, "Te": 160.50, "rms": 0.59, "QDeg": 0.00},
		{"Ts": 160.50, "Te": 160.75, "rms": 0.64, "QDeg": 0.00},
		{"Ts": 160.75, "Te": 161.00, "rms": 0.71, "QDeg": 0.00},
		{"Ts": 161.00, "Te": 161.25, "rms": 0.75, "QDeg": 0.00},
		{"Ts": 161.25, "Te": 161.50, "rms": 0.74, "QDeg": 0.00},
		{"Ts": 161.50, "Te": 161.75, "rms": 0.72, "QDeg": 0.00},
		{"Ts": 161.75, "Te": 162.00, "rms": 0.69, "QDeg": 0.00},
		{"Ts": 162.00, "Te": 162.25, "rms": 0.74, "QDeg": 0.00},
		{"Ts": 162.25, "Te": 162.50, "rms": 0.75, "QDeg": 0.00},
		{"Ts": 162.50, "Te": 162.75, "rms": 0.75, "QDeg": 0.00},
		{"Ts": 162.75, "Te": 163.00, "rms": 0.77, "QDeg": 0.00},
		{"Ts": 163.00, "Te": 163.25, "rms": 0.74, "QDeg": 0.00},
		{"Ts": 163.25, "Te": 163.50, "rms": 0.78, "QDeg": 0.00},
		{"Ts": 163.50, "Te": 163.75, "rms": 0.80, "QDeg": 0.00},
		{"Ts": 163.75, "Te": 164.00, "rms": 0.77, "QDeg": 1.56},
		{"Ts": 164.00, "Te": 164.25, "rms": 0.75, "QDeg": 3.12},
		{"Ts": 164.25, "Te": 164.50, "rms": 0.67, "QDeg": 4.69},
		{"Ts": 164.50, "Te": 164.75, "rms": 0.61, "QDeg": 7.81},
		{"Ts": 164.75, "Te": 165.00, "rms": 0.58, "QDeg": 7.81},
		{"Ts": 165.00, "Te": 165.24, "rms": 0.55, "QDeg": 7.81},
		{"Ts": 165.24, "Te": 165.49, "rms": 0.59, "QDeg": 7.81},
		{"Ts": 165.49, "Te": 165.74, "rms": 0.62, "QDeg": 4.69},
		{"Ts": 165.74, "Te": 165.99, "rms": 0.74, "QDeg": 3.12},
		{"Ts": 165.99, "Te": 166.24, "rms": 0.77, "QDeg": 1.56},
		{"Ts": 166.24, "Te": 166.49, "rms": 0.83, "QDeg": 0.00},
		{"Ts": 166.49, "Te": 166.74, "rms": 0.80, "QDeg": 0.00},
		{"Ts": 166.74, "Te": 166.99, "rms": 0.87, "QDeg": 0.00},
		{"Ts": 166.99, "Te": 167.24, "rms": 0.99, "QDeg": 0.00},
		{"Ts": 167.24, "Te": 167.49, "rms": 0.97, "QDeg": 0.00},
		{"Ts": 167.49, "Te": 167.74, "rms": 0.99, "QDeg": 0.00},
		{"Ts": 167.74, "Te": 167.99, "rms": 1.00, "QDeg": 0.00},
		{"Ts": 167.99, "Te": 168.24, "rms": 0.94, "QDeg": 0.00},
		{"Ts": 168.24, "Te": 168.49, "rms": 1.01, "QDeg": 0.00},
		{"Ts": 168.49, "Te": 168.74, "rms": 1.09, "QDeg": 0.00},
		{"Ts": 168.74, "Te": 168.99, "rms": 0.96, "QDeg": 0.00},
		{"Ts": 168.99, "Te": 169.24, "rms": 1.14, "QDeg": 0.00},
		{"Ts": 169.24, "Te": 169.49, "rms": 1.14, "QDeg": 0.00},
		{"Ts": 169.49, "Te": 169.74, "rms": 1.14, "QDeg": 0.00},
		{"Ts": 169.74, "Te": 169.99, "rms": 1.36, "QDeg": 0.00},
		{"Ts": 169.99, "Te": 170.24, "rms": 1.22, "QDeg": 0.00},
		{"Ts": 170.24, "Te": 170.49, "rms": 1.21, "QDeg": 0.00},
		{"Ts": 170.49, "Te": 170.74, "rms": 1.17, "QDeg": 0.00},
		{"Ts": 170.74, "Te": 170.99, "rms": 1.09, "QDeg": 0.00},
		{"Ts": 170.99, "Te": 171.24, "rms": 1.10, "QDeg": 0.00},
		{"Ts": 171.24, "Te": 171.49, "rms": 1.09, "QDeg": 0.00},
		{"Ts": 171.49, "Te": 171.73, "rms": 1.22, "QDeg": 0.00},
		{"Ts": 171.73, "Te": 171.98, "rms": 1.16, "QDeg": 0.00},
		{"Ts": 171.98, "Te": 172.23, "rms": 1.15, "QDeg": 0.00},
		{"Ts": 172.23, "Te": 172.48, "rms": 1.10, "QDeg": 0.00},
		{"Ts": 172.48, "Te": 172.73, "rms": 0.91, "QDeg": 0.00},
		{"Ts": 172.73, "Te": 172.98, "rms": 0.79, "QDeg": 0.00},
		{"Ts": 172.98, "Te": 173.23, "rms": 0.71, "QDeg": 0.00},
		{"Ts": 173.23, "Te": 173.48, "rms": 0.69, "QDeg": 0.00},
		{"Ts": 173.48, "Te": 173.73, "rms": 0.68, "QDeg": 0.00},
		{"Ts": 173.73, "Te": 173.98, "rms": 0.69, "QDeg": 0.00},
		{"Ts": 173.98, "Te": 174.23, "rms": 0.68, "QDeg": 0.00},
		{"Ts": 174.23, "Te": 174.48, "rms": 0.67, "QDeg": 0.00},
		{"Ts": 174.48, "Te": 174.73, "rms": 0.67, "QDeg": 0.00},
		{"Ts": 174.73, "Te": 174.98, "rms": 0.65, "QDeg": 0.00},
		{"Ts": 174.98, "Te": 175.23, "rms": 0.65, "QDeg": 0.00},
		{"Ts": 175.23, "Te": 175.48, "rms": 0.66, "QDeg": 0.00},
		{"Ts": 175.48, "Te": 175.73, "rms": 0.71, "QDeg": 0.00},
		{"Ts": 175.73, "Te": 175.98, "rms": 0.75, "QDeg": 0.00},
		{"Ts": 175.98, "Te": 176.23, "rms": 0.76, "QDeg": 0.00},
		{"Ts": 176.23, "Te": 176.48, "rms": 0.75, "QDeg": 0.00},
		{"Ts": 176.48, "Te": 176.73, "rms": 0.70, "QDeg": 0.00},
		{"Ts": 176.73, "Te": 176.98, "rms": 0.67, "QDeg": 0.00},
		{"Ts": 176.98, "Te": 177.23, "rms": 0.65, "QDeg": 0.00},
		{"Ts": 177.23, "Te": 177.48, "rms": 0.66, "QDeg": 0.00},
		{"Ts": 177.48, "Te": 177.73, "rms": 0.68, "QDeg": 0.00},
		{"Ts": 177.73, "Te": 177.98, "rms": 0.71, "QDeg": 0.00},
		{"Ts": 177.98, "Te": 178.22, "rms": 0.74, "QDeg": 0.00},
		{"Ts": 178.22, "Te": 178.47, "rms": 0.73, "QDeg": 0.00},
		{"Ts": 178.47, "Te": 178.72, "rms": 0.72, "QDeg": 0.00},
		{"Ts": 178.72, "Te": 178.97, "rms": 0.71, "QDeg": 0.00},
		{"Ts": 178.97, "Te": 179.22, "rms": 0.68, "QDeg": 0.00},
		{"Ts": 179.22, "Te": 179.47, "rms": 0.69, "QDeg": 0.00},
		{"Ts": 179.47, "Te": 179.72, "rms": 0.69, "QDeg": 0.00},
		{"Ts": 179.72, "Te": 179.97, "rms": 0.67, "QDeg": 0.00},
		{"Ts": 179.97, "Te": 180.22, "rms": 0.68, "QDeg": 0.00},
		{"Ts": 180.22, "Te": 180.47, "rms": 0.67, "QDeg": 0.00},
		{"Ts": 180.47, "Te": 180.72, "rms": 0.69, "QDeg": 0.00},
		{"Ts": 180.72, "Te": 180.97, "rms": 0.68, "QDeg": 0.00},
		{"Ts": 180.97, "Te": 181.22, "rms": 0.70, "QDeg": 0.00},
		{"Ts": 181.22, "Te": 181.47, "rms": 0.72, "QDeg": 0.00},
		{"Ts": 181.47, "Te": 181.72, "rms": 0.77, "QDeg": 0.00},
		{"Ts": 181.72, "Te": 181.97, "rms": 0.81, "QDeg": 0.00},
		{"Ts": 181.97, "Te": 182.22, "rms": 0.83, "QDeg": 0.00},
		{"Ts": 182.22, "Te": 182.47, "rms": 0.82, "QDeg": 0.00},
		{"Ts": 182.47, "Te": 182.72, "rms": 0.78, "QDeg": 0.00},
		{"Ts": 182.72, "Te": 182.97, "rms": 0.77, "QDeg": 0.00},
		{"Ts": 182.97, "Te": 183.22, "rms": 0.00, "QDeg": 0.00},
		{"Ts": 183.22, "Te": 183.47, "rms": 0.00, "QDeg": 0.00},
		{"Ts": 183.47, "Te": 183.72, "rms": 0.00, "QDeg": 0.00},
		{"Ts": 183.72, "Te": 183.97, "rms": 0.00, "QDeg": 0.00}
	],
	"AveRmsWQual":
 	 [ 
		83.2
		],
	"Distortion free regions":
 	 [
		{"s": 0.00, "e": 38.44},
		{"s": 39.94, "e": 40.69},
		{"s": 43.18, "e": 183.97}
	]
}
